sshmap/__init__.py
sshmap/callback.py
sshmap/defaults.py
sshmap/jupyter.py
sshmap/package_metadata.json
sshmap/runner.py
sshmap/sshmap.py
sshmap/utility.py
sshmap-1.0.227.data/scripts/sshmap
sshmap-1.0.227.dist-info/DESCRIPTION.rst
sshmap-1.0.227.dist-info/METADATA
sshmap-1.0.227.dist-info/RECORD
sshmap-1.0.227.dist-info/WHEEL
sshmap-1.0.227.dist-info/metadata.json
sshmap-1.0.227.dist-info/top_level.txt
